pygame_gesture_kit/__init__.py
pygame_gesture_kit/camera.py
pygame_gesture_kit/gesture_recognizer.py
pygame_gesture_kit/hand.py
pygame_gesture_kit/hand_visualizer.py
pygame_gesture_kit/example/__init__.py
pygame_gesture_kit/example/main.py
pygame_gesture_kit/model/hagrid.task
pygame_gesture_kit/model/rps.task
pygame_gesture_kit-0.0.2.dist-info/LICENSE
pygame_gesture_kit-0.0.2.dist-info/METADATA
pygame_gesture_kit-0.0.2.dist-info/WHEEL
pygame_gesture_kit-0.0.2.dist-info/top_level.txt
pygame_gesture_kit-0.0.2.dist-info/RECORD
