Metadata-Version: 2.1
Name: pygame_gesture_kit
Version: 0.0.2
Summary: Camera based hand tracking and gesture recognition for pygame
Author-email: Daniel Arnold <pypi@darnold.org>
Project-URL: Homepage, https://github.com/FreeBugs/pygame_gesture_kit
Project-URL: Issues, https://github.com/FreeBugs/pygame_gesture_kit/issues
Classifier: Programming Language :: Python :: 3
Classifier: License :: OSI Approved :: GNU Library or Lesser General Public License (LGPL)
Classifier: Operating System :: OS Independent
Classifier: Topic :: Games/Entertainment
Classifier: Topic :: Multimedia :: Graphics
Classifier: Topic :: Multimedia :: Graphics :: Capture :: Digital Camera
Classifier: Operating System :: Microsoft :: Windows
Classifier: Operating System :: POSIX
Classifier: Operating System :: Unix
Classifier: Operating System :: MacOS
Requires-Python: >=3.8
License-File: LICENSE
Requires-Dist: pygame
Requires-Dist: mediapipe
Requires-Dist: numpy
Requires-Dist: opencv-python
Requires-Dist: importlib-resources
